milvus_helper/__init__.py
milvus_helper/client.py
milvus_helper-0.1.0.dist-info/licenses/LICENSE
milvus_helper-0.1.0.dist-info/METADATA
milvus_helper-0.1.0.dist-info/WHEEL
milvus_helper-0.1.0.dist-info/top_level.txt
milvus_helper-0.1.0.dist-info/RECORD
