Metadata-Version: 2.4
Name: milvus-helper
Version: 0.1.0
Summary: A wrapper around pymilvus to simplify common operations.
Author-email: Yuxin Fan <lawrence.yuxinfan@outlook.com>
License: MIT
Project-URL: Homepage, https://github.com/yx-fan/milvus-helper
Project-URL: Source, https://github.com/yx-fan/milvus-helper
Project-URL: Bug Tracker, https://github.com/yx-fan/milvus-helper/issues
Requires-Python: >=3.8
License-File: LICENSE
Requires-Dist: pymilvus>=2.4.3
Requires-Dist: numpy
Requires-Dist: pandas
Provides-Extra: dev
Requires-Dist: pytest; extra == "dev"
Dynamic: license-file
